minerl_wrappers/__init__.py
minerl_wrappers/config.py
minerl_wrappers/core/__init__.py
minerl_wrappers/core/action_repeat_wrapper.py
minerl_wrappers/core/action_wrapper.py
minerl_wrappers/core/deterministic_wrapper.py
minerl_wrappers/core/discrete_action_wrapper.py
minerl_wrappers/core/gray_scale_wrapper.py
minerl_wrappers/core/normalize.py
minerl_wrappers/core/observation_stack_wrapper.py
minerl_wrappers/core/observation_wrapper.py
minerl_wrappers/data/means.npy
minerl_wrappers/diamond_wrappers.py
minerl_wrappers/pfrl/__init__.py
minerl_wrappers/pfrl/wrappers/__init__.py
minerl_wrappers/pfrl/wrappers/atari_wrappers.py
minerl_wrappers/pfrl/wrappers/continuing_time_limit.py
minerl_wrappers/pfrl/wrappers/monitor.py
minerl_wrappers/pfrl/wrappers/randomize_action.py
minerl_wrappers/pfrl_2019_wrappers.py
minerl_wrappers/pfrl_2020_wrappers.py
minerl_wrappers/utils.py
minerl_wrappers/wrap.py
minerl_wrappers-0.1.6.dist-info/LICENSE.md
minerl_wrappers-0.1.6.dist-info/WHEEL
minerl_wrappers-0.1.6.dist-info/METADATA
minerl_wrappers-0.1.6.dist-info/RECORD
