Metadata-Version: 2.1
Name: minerl-wrappers
Version: 0.1.6
Summary: minerl-wrappers compiles common wrappers and standardizes code for reproducibility in the MineRL environment!
Home-page: https://github.com/minerl-wrappers/minerl-wrappers/
License: GPL-3.0-only
Author: Julius Frost
Requires-Python: >=3.7,<4.0
Classifier: License :: OSI Approved :: GNU General Public License v3 (GPLv3)
Classifier: Programming Language :: Python :: 3
Classifier: Programming Language :: Python :: 3.7
Classifier: Programming Language :: Python :: 3.8
Classifier: Programming Language :: Python :: 3.9
Requires-Dist: PyYAML
Requires-Dist: gym
Requires-Dist: minerl (>=0.4.0,<0.5.0)
Requires-Dist: numpy
Requires-Dist: opencv-python
Project-URL: Repository, https://github.com/minerl-wrappers/minerl-wrappers/
